{
    "name": "Peaks Island",
    "code": "CBL_PEAKS",
    "destination": {
        "name": "Peaks Island",
        "description": "Forest City Landing",
        "coordinate": "43.655538,-70.199288"
    },
    "origin": {
        "name": "Portland",
        "description": "Casco Bay Lines Ferry Terminal",
        "coordinate": "43.6570177,-70.248711"
    },
    "schedules": [
        {
            "season": "Spring",
            "dates": "2016-04-16,2016-06-17",
            "holidays":[
                {
                    "name":"Memorial Day",
                    "date":"2016-05-30"
                }
            ],
            "departures": []
        }
    ]
}